renci_ner/__init__.py
renci_ner/core.py
renci_ner/py.typed
renci_ner/services/__init__.py
renci_ner/services/linkers/__init__.py
renci_ner/services/linkers/babelsapbert.py
renci_ner/services/linkers/nameres.py
renci_ner/services/ner/__init__.py
renci_ner/services/ner/biomegatron.py
renci_ner/services/normalization/__init__.py
renci_ner/services/normalization/nodenorm.py
renci_ner-1.0.1.dist-info/METADATA
renci_ner-1.0.1.dist-info/WHEEL
renci_ner-1.0.1.dist-info/licenses/LICENSE
renci_ner-1.0.1.dist-info/RECORD
