Metadata-Version: 2.4
Name: renci-ner
Version: 1.0.1
Summary: A library for accessing RENCI NER services.
Author-email: Gaurav Vaidya <gaurav@renci.org>
License-File: LICENSE
Keywords: biomedical,named entity linking,named entity recognition,natural language processing,ner,nlp
Classifier: Development Status :: 4 - Beta
Classifier: Intended Audience :: Developers
Classifier: License :: OSI Approved :: MIT License
Classifier: Operating System :: OS Independent
Classifier: Programming Language :: Python :: 3 :: Only
Classifier: Programming Language :: Python :: 3.11
Classifier: Programming Language :: Python :: 3.12
Classifier: Programming Language :: Python :: 3.13
Requires-Python: >=3.11
Requires-Dist: requests>=2.32.3
